unico/__init__.py
unico/exceptions.py
unico/modules/agents.py
unico/modules/completions.py
unico/modules/contexts.py
unico_python-0.1.0.dist-info/METADATA
unico_python-0.1.0.dist-info/WHEEL
unico_python-0.1.0.dist-info/top_level.txt
unico_python-0.1.0.dist-info/RECORD
