Metadata-Version: 2.4
Name: unico-python
Version: 0.1.0
Summary: Python Client for the UNICO Api
Author-email: UNICO <info@theunico.it>
License: MIT
Keywords: api,client,unico,requests,python
Requires-Python: >=3.11
Requires-Dist: requests
